rsproduction/__init__.py
rsproduction/styling/__init__.py
rsproduction/styling/color/__init__.py
rsproduction/styling/color/color.py
rsproduction/userinterface/__init__.py
rsproduction/userinterface/userinterface.py
rsproduction-0.0.18.dist-info/LICENSE
rsproduction-0.0.18.dist-info/METADATA
rsproduction-0.0.18.dist-info/WHEEL
rsproduction-0.0.18.dist-info/top_level.txt
rsproduction-0.0.18.dist-info/RECORD
